lista_1/priority.v
module prio2(
    input wire[1: 0] i,
    output wire o,
    output wire valid
);

    or #1 or1(valid, i[0], i[1]);
    assign o = i[1];
endmodule

module prio4(
    input wire[3:0] i,
    output wire[1:0] o,
    output wire valid
);

    wire out1, valid1, out2, valid2;
    prio2 #1 p1(.i({i[3], i[2]}), .o(out1), .valid(valid1));
    prio2 #1 p2(.i({i[1], i[0]}), .o(out2), .valid(valid2));
    prio2 #1 p3(.i({valid1, valid2}), .o(o[1]), .valid(valid));

    wire mux1, mux2, muxneg;
    not #1 n1(muxneg, o[1]);
    and #1 a1(mux1, out1, o[1]);
    and #1 a2(mux2, out2, muxneg);

    or #1 or1(o[0], mux1, mux2);
endmodule

module test;
    reg [3:0] in = 0;
    wire valid;
    wire[1:0] out;

    initial begin
        $dumpfile("test.vcd");
        $dumpvars(0, test);
        #15
        in <= 4'b1000;
        #15
        in <= 4'b0100;
        #15
        in <= 4'b0010;
        #15
        in <= 4'b0001;

        #15
        in <= 4'b1100;
        #15
        in <= 4'b1110;
        #15
        in <= 4'b0011;
        #15
        in <= 4'b0001;
        #15
        in <= 4'b0000;
        #15
        in <= 4'b1111;
        #100 $finish;
    end

    prio4 a(
        .i(in),
        .o(out),
        .valid(valid)
    );

    initial $monitor ("%t %h %h %0d", $time, in, out, valid);
endmodule //test

lista_1/test.vcd
$date
	Thu Oct 14 16:45:21 2021
$end
$version
	Icarus Verilog
$end
$timescale
	1s
$end
$scope module test $end
$var wire 1 ! valid $end
$var wire 2 " out [1:0] $end
$var reg 4 # in [3:0] $end
$scope module a $end
$var wire 4 $ i [3:0] $end
$var wire 1 % mux1 $end
$var wire 1 & mux2 $end
$var wire 1 ' muxneg $end
$var wire 1 ( valid2 $end
$var wire 1 ) valid1 $end
$var wire 1 ! valid $end
$var wire 1 * out2 $end
$var wire 1 + out1 $end
$var wire 2 , o [1:0] $end
$scope module p1 $end
$var wire 2 - i [1:0] $end
$var wire 1 ) valid $end
$var wire 1 + o $end
$upscope $end
$scope module p2 $end
$var wire 2 . i [1:0] $end
$var wire 1 ( valid $end
$var wire 1 * o $end
$upscope $end
$scope module p3 $end
$var wire 2 / i [1:0] $end
$var wire 1 ! valid $end
$var wire 1 0 o $end
$upscope $end
$upscope $end
$upscope $end
$enddefinitions $end
#0
$dumpvars
x0
bx /
b0 .
b0 -
bx ,
0+
0*
x)
x(
x'
x&
x%
b0 $
b0 #
bx "
x!
$end
#1
b0x "
b0x ,
00
0%
0)
0&
b0 /
0(
#2
1'
0!
b0 "
b0 ,
#15
1+
b10 -
b1000 #
b1000 $
#16
b10 "
b10 ,
10
b10 /
1)
#17
1%
0'
1!
#18
b11 "
b11 ,
#30
0+
b1 -
b100 #
b100 $
#31
0%
#32
b10 "
b10 ,
#45
1*
b0 -
b10 .
b10 #
b10 $
#46
b0 "
b0 ,
00
0)
b1 /
1(
#47
1'
#48
1&
#49
b1 "
b1 ,
#60
0*
b1 .
b1 #
b1 $
#61
0&
#62
b0 "
b0 ,
#75
1+
b11 -
b0 .
b1100 #
b1100 $
#76
b10 "
b10 ,
10
1)
b10 /
0(
#77
1%
0'
#78
b11 "
b11 ,
#90
1*
b10 .
b1110 #
b1110 $
#91
b11 /
1(
#105
0+
b0 -
b11 .
b11 #
b11 $
#106
b1 "
b1 ,
00
0%
b1 /
0)
#107
1'
b0 "
b0 ,
#108
1&
#109
b1 "
b1 ,
#120
0*
b1 .
b1 #
b1 $
#121
0&
#122
b0 "
b0 ,
#135
b0 .
b0 #
b0 $
#136
b0 /
0(
#137
0!
#150
1+
1*
b11 -
b11 .
b1111 #
b1111 $
#151
b10 "
b10 ,
10
1)
1&
b11 /
1(
#152
1%
0'
1!
b11 "
b11 ,
#153
0&
