lista_3/bcd_verilator.v
`default_nettype none

/* verilator lint_off DECLFILENAME */
module BCDC#( 
    parameter rstat = 10
) (
    input wire trigger,
    input wire reset,
    output wire next,
    output wire [3:0] BCD
);

    reg [3:0] istate;
    reg inext;

    assign next = inext;
    assign BCD = istate;

    always @(posedge trigger or posedge reset) begin
        if (reset) begin
            istate <= 4'b0000;
            inext <= 1'b0;
        end else begin
            if (istate == rstat) begin
                istate <= 4'b0000;
                inext <= 1'b1;
            end else begin
                if (istate == 4'b0001) begin
                    inext <= 1'b0;
                end 
                istate <= istate + 1'b1;
            end
        end
    end
endmodule //BCDC
/* verilator lint_on DECLFILENAME */

module bcd_verilator(
    input wire clk,
    input wire reset,
    output wire [3:0] BCD_SL,
    output wire [3:0] BCD_SH,
    output wire [3:0] BCD_ML,
    output wire [3:0] BCD_MH
);

    wire SHT, MLT, MHT, trash;
    BCDC #(.rstat(9)) SL(.trigger(clk), .reset(reset), .next(SHT), .BCD(BCD_SL));
    BCDC #(.rstat(5)) SH(.trigger(SHT), .reset(reset), .next(MLT), .BCD(BCD_SH));
    BCDC #(.rstat(9)) ML(.trigger(MLT), .reset(reset), .next(MHT), .BCD(BCD_ML));
    BCDC #(.rstat(5)) MH(.trigger(MHT), .reset(reset), .next(trash), .BCD(BCD_MH));

endmodule //bcd_verilator

lista_3/bcdclk.v
`default_nettype none

module timert(
    input wire clk,
    input wire reset,
    output wire [3:0] BCD_SL,
    output wire [3:0] BCD_SH,
    output wire [3:0] BCD_ML,
    output wire [3:0] BCD_MH
);

    wire SHT, MLT, MHT, trash;
    BCDC #(.rstat(9)) SL(.trigger(clk), .reset(reset), .next(SHT), .BCD(BCD_SL));
    BCDC #(.rstat(5)) SH(.trigger(SHT), .reset(reset), .next(MLT), .BCD(BCD_SH));
    BCDC #(.rstat(9)) ML(.trigger(MLT), .reset(reset), .next(MHT), .BCD(BCD_ML));
    BCDC #(.rstat(5)) MH(.trigger(MHT), .reset(reset), .next(trash), .BCD(BCD_MH));
endmodule //timert

module testbench;
    reg reset = 0;
    reg clk = 0;
    wire [3:0] BCD_SL;
    wire [3:0] BCD_SH;
    wire [3:0] BCD_ML;
    wire [3:0] BCD_MH;

    initial begin
        $dumpfile("test.vcd");
        $dumpvars(0, testbench);
        #2 reset = 0;
        #2 reset = 1;
        #2 reset = 0;
        #7400 $finish;
    end

    always #1 clk = !clk;

    timert t(
        .clk(clk), .reset(reset),
        .BCD_SL(BCD_SL),
        .BCD_SH(BCD_SH),
        .BCD_ML(BCD_ML),
        .BCD_MH(BCD_MH)
    );

    initial $monitor ($time, clk, reset, BCD_SL, BCD_SH, BCD_ML, BCD_MH);

    always #1 clk = !clk;
endmodule //testbench

lista_3/test.vcd
$date
	Thu Oct 28 17:25:59 2021
$end
$version
	Icarus Verilog
$end
$timescale
	1s
$end
$scope module testbench $end
$var wire 4 ! BCD_SL [3:0] $end
$var wire 4 " BCD_SH [3:0] $end
$var wire 4 # BCD_ML [3:0] $end
$var wire 4 $ BCD_MH [3:0] $end
$var reg 1 % clk $end
$var reg 1 & reset $end
$scope module t $end
$var wire 1 % clk $end
$var wire 1 & reset $end
$var wire 1 ' trash $end
$var wire 1 ( SHT $end
$var wire 1 ) MLT $end
$var wire 1 * MHT $end
$var wire 4 + BCD_SL [3:0] $end
$var wire 4 , BCD_SH [3:0] $end
$var wire 4 - BCD_ML [3:0] $end
$var wire 4 . BCD_MH [3:0] $end
$scope module MH $end
$var wire 4 / BCD [3:0] $end
$var wire 1 ' next $end
$var wire 1 & reset $end
$var wire 1 * trigger $end
$var reg 1 0 inext $end
$var reg 4 1 istate [3:0] $end
$upscope $end
$scope module ML $end
$var wire 4 2 BCD [3:0] $end
$var wire 1 * next $end
$var wire 1 & reset $end
$var wire 1 ) trigger $end
$var reg 1 3 inext $end
$var reg 4 4 istate [3:0] $end
$upscope $end
$scope module SH $end
$var wire 4 5 BCD [3:0] $end
$var wire 1 ) next $end
$var wire 1 & reset $end
$var wire 1 ( trigger $end
$var reg 1 6 inext $end
$var reg 4 7 istate [3:0] $end
$upscope $end
$scope module SL $end
$var wire 4 8 BCD [3:0] $end
$var wire 1 ( next $end
$var wire 1 & reset $end
$var wire 1 % trigger $end
$var reg 1 9 inext $end
$var reg 4 : istate [3:0] $end
$upscope $end
$upscope $end
$upscope $end
$enddefinitions $end
#0
$dumpvars
bx :
x9
bx 8
bx 7
x6
bx 5
bx 4
x3
bx 2
bx 1
x0
bx /
bx .
bx -
bx ,
bx +
x*
x)
x(
x'
0&
0%
bx $
bx #
bx "
bx !
$end
#1
0%
#2
0%
#3
0%
#4
0'
00
b0 $
b0 .
b0 /
b0 1
0*
03
b0 #
b0 -
b0 2
b0 4
0)
06
b0 "
b0 ,
b0 5
b0 7
0(
09
b0 !
b0 +
b0 8
b0 :
0%
1&
#5
0%
#6
b1 !
b1 +
b1 8
b1 :
0%
0&
#7
b10 !
b10 +
b10 8
b10 :
0%
#8
b11 !
b11 +
b11 8
b11 :
0%
#9
b100 !
b100 +
b100 8
b100 :
0%
#10
b101 !
b101 +
b101 8
b101 :
0%
#11
b110 !
b110 +
b110 8
b110 :
0%
#12
b111 !
b111 +
b111 8
b111 :
0%
#13
b1000 !
b1000 +
b1000 8
b1000 :
0%
#14
b1001 !
b1001 +
b1001 8
b1001 :
0%
#15
b1 "
b1 ,
b1 5
b1 7
1(
19
b0 !
b0 +
b0 8
b0 :
0%
#16
b1 !
b1 +
b1 8
b1 :
0%
#17
b10 !
b10 +
b10 8
b10 :
0(
09
0%
#18
b11 !
b11 +
b11 8
b11 :
0%
#19
b100 !
b100 +
b100 8
b100 :
0%
#20
b101 !
b101 +
b101 8
b101 :
0%
#21
b110 !
b110 +
b110 8
b110 :
0%
#22
b111 !
b111 +
b111 8
b111 :
0%
#23
b1000 !
b1000 +
b1000 8
b1000 :
0%
#24
b1001 !
b1001 +
b1001 8
b1001 :
0%
#25
b10 "
b10 ,
b10 5
b10 7
1(
19
b0 !
b0 +
b0 8
b0 :
0%
#26
b1 !
b1 +
b1 8
b1 :
0%
#27
b10 !
b10 +
b10 8
b10 :
0(
09
0%
#28
b11 !
b11 +
b11 8
b11 :
0%
#29
b100 !
b100 +
b100 8
b100 :
0%
#30
b101 !
b101 +
b101 8
b101 :
0%
#31
b110 !
b110 +
b110 8
b110 :
0%
#32
b111 !
b111 +
b111 8
b111 :
0%
#33
b1000 !
b1000 +
b1000 8
b1000 :
0%
#34
b1001 !
b1001 +
b1001 8
b1001 :
0%
#35
b11 "
b11 ,
b11 5
b11 7
1(
19
b0 !
b0 +
b0 8
b0 :
0%
#36
b1 !
b1 +
b1 8
b1 :
0%
#37
b10 !
b10 +
b10 8
b10 :
0(
09
0%
#38
b11 !
b11 +
b11 8
b11 :
0%
#39
b100 !
b100 +
b100 8
b100 :
0%
#40
b101 !
b101 +
b101 8
b101 :
0%
#41
b110 !
b110 +
b110 8
b110 :
0%
#42
b111 !
b111 +
b111 8
b111 :
0%
#43
b1000 !
b1000 +
b1000 8
b1000 :
0%
#44
b1001 !
b1001 +
b1001 8
b1001 :
0%
#45
b100 "
b100 ,
b100 5
b100 7
1(
19
b0 !
b0 +
b0 8
b0 :
0%
#46
b1 !
b1 +
b1 8
b1 :
0%
#47
b10 !
b10 +
b10 8
b10 :
0(
09
0%
#48
b11 !
b11 +
b11 8
b11 :
0%
#49
b100 !
b100 +
b100 8
b100 :
0%
#50
b101 !
b101 +
b101 8
b101 :
0%
#51
b110 !
b110 +
b110 8
b110 :
0%
#52
b111 !
b111 +
b111 8
b111 :
0%
#53
b1000 !
b1000 +
b1000 8
b1000 :
0%
#54
b1001 !
b1001 +
b1001 8
b1001 :
0%
#55
b101 "
b101 ,
b101 5
b101 7
1(
19
b0 !
b0 +
b0 8
b0 :
0%
#56
b1 !
b1 +
b1 8
b1 :
0%
#57
b10 !
b10 +
b10 8
b10 :
0(
09
0%
#58
b11 !
b11 +
b11 8
b11 :
0%
#59
b100 !
b100 +
b100 8
b100 :
0%
#60
b101 !
b101 +
b101 8
b101 :
0%
#61
b110 !
b110 +
b110 8
b110 :
0%
#62
b111 !
b111 +
b111 8
b111 :
0%
#63
b1000 !
b1000 +
b1000 8
b1000 :
0%
#64
b1001 !
b1001 +
b1001 8
b1001 :
0%
#65
b1 #
b1 -
b1 2
b1 4
1)
16
b0 "
b0 ,
b0 5
b0 7
1(
19
b0 !
b0 +
b0 8
b0 :
0%
#66
b1 !
b1 +
b1 8
b1 :
0%
#67
b10 !
b10 +
b10 8
b10 :
0(
09
0%
#68
b11 !
b11 +
b11 8
b11 :
0%
#69
b100 !
b100 +
b100 8
b100 :
0%
#70
b101 !
b101 +
b101 8
b101 :
0%
#71
b110 !
b110 +
b110 8
b110 :
0%
#72
b111 !
b111 +
b111 8
b111 :
0%
#73
b1000 !
b1000 +
b1000 8
b1000 :
0%
#74
b1001 !
b1001 +
b1001 8
b1001 :
0%
#75
b1 "
b1 ,
b1 5
b1 7
1(
19
b0 !
b0 +
b0 8
b0 :
0%
#76
b1 !
b1 +
b1 8
b1 :
0%
#77
b10 !
b10 +
b10 8
b10 :
0(
09
0%
#78
b11 !
b11 +
b11 8
b11 :
0%
#79
b100 !
b100 +
b100 8
b100 :
0%
#80
b101 !
b101 +
b101 8
b101 :
0%
#81
b110 !
b110 +
b110 8
b110 :
0%
#82
b111 !
b111 +
b111 8
b111 :
0%
#83
b1000 !
b1000 +
b1000 8
b1000 :
0%
#84
b1001 !
b1001 +
b1001 8
b1001 :
0%
#85
b10 "
b10 ,
b10 5
b10 7
0)
06
1(
19
b0 !
b0 +
b0 8
b0 :
0%
#86
b1 !
b1 +
b1 8
b1 :
0%
#87
b10 !
b10 +
b10 8
b10 :
0(
09
0%
#88
b11 !
b11 +
b11 8
b11 :
0%
#89
b100 !
b100 +
b100 8
b100 :
0%
#90
b101 !
b101 +
b101 8
b101 :
0%
#91
b110 !
b110 +
b110 8
b110 :
0%
#92
b111 !
b111 +
b111 8
b111 :
0%
#93
b1000 !
b1000 +
b1000 8
b1000 :
0%
#94
b1001 !
b1001 +
b1001 8
b1001 :
0%
#95
b11 "
b11 ,
b11 5
b11 7
1(
19
b0 !
b0 +
b0 8
b0 :
0%
#96
b1 !
b1 +
b1 8
b1 :
0%
#97
b10 !
b10 +
b10 8
b10 :
0(
09
0%
#98
b11 !
b11 +
b11 8
b11 :
0%
#99
b100 !
b100 +
b100 8
b100 :
0%
#100
b101 !
b101 +
b101 8
b101 :
0%
#101
b110 !
b110 +
b110 8
b110 :
0%
#102
b111 !
b111 +
b111 8
b111 :
0%
#103
b1000 !
b1000 +
b1000 8
b1000 :
0%
#104
b1001 !
b1001 +
b1001 8
b1001 :
0%
#105
b100 "
b100 ,
b100 5
b100 7
1(
19
b0 !
b0 +
b0 8
b0 :
0%
#106
b1 !
b1 +
b1 8
b1 :
0%
#107
b10 !
b10 +
b10 8
b10 :
0(
09
0%
#108
b11 !
b11 +
b11 8
b11 :
0%
#109
b100 !
b100 +
b100 8
b100 :
0%
#110
b101 !
b101 +
b101 8
b101 :
0%
#111
b110 !
b110 +
b110 8
b110 :
0%
#112
b111 !
b111 +
b111 8
b111 :
0%
#113
b1000 !
b1000 +
b1000 8
b1000 :
0%
#114
b1001 !
b1001 +
b1001 8
b1001 :
0%
#115
b101 "
b101 ,
b101 5
b101 7
1(
19
b0 !
b0 +
b0 8
b0 :
0%
#116
b1 !
b1 +
b1 8
b1 :
0%
#117
b10 !
b10 +
b10 8
b10 :
0(
09
0%
#118
b11 !
b11 +
b11 8
b11 :
0%
#119
b100 !
b100 +
b100 8
b100 :
0%
#120
b101 !
b101 +
b101 8
b101 :
0%
#121
b110 !
b110 +
b110 8
b110 :
0%
#122
b111 !
b111 +
b111 8
b111 :
0%
#123
b1000 !
b1000 +
b1000 8
b1000 :
0%
#124
b1001 !
b1001 +
b1001 8
b1001 :
0%
#125
b10 #
b10 -
b10 2
b10 4
1)
16
b0 "
b0 ,
b0 5
b0 7
1(
19
b0 !
b0 +
b0 8
b0 :
0%
#126
b1 !
b1 +
b1 8
b1 :
0%
#127
b10 !
b10 +
b10 8
b10 :
0(
09
0%
#128
b11 !
b11 +
b11 8
b11 :
0%
#129
b100 !
b100 +
b100 8
b100 :
0%
#130
b101 !
b101 +
b101 8
b101 :
0%
#131
b110 !
b110 +
b110 8
b110 :
0%
#132
b111 !
b111 +
b111 8
b111 :
0%
#133
b1000 !
b1000 +
b1000 8
b1000 :
0%
#134
b1001 !
b1001 +
b1001 8
b1001 :
0%
#135
b1 "
b1 ,
b1 5
b1 7
1(
19
b0 !
b0 +
b0 8
b0 :
0%
#136
b1 !
b1 +
b1 8
b1 :
0%
#137
b10 !
b10 +
b10 8
b10 :
0(
09
0%
#138
b11 !
b11 +
b11 8
b11 :
0%
#139
b100 !
b100 +
b100 8
b100 :
0%
#140
b101 !
b101 +
b101 8
b101 :
0%
#141
b110 !
b110 +
b110 8
b110 :
0%
#142
b111 !
b111 +
b111 8
b111 :
0%
#143
b1000 !
b1000 +
b1000 8
b1000 :
0%
#144
b1001 !
b1001 +
b1001 8
b1001 :
0%
#145
b10 "
b10 ,
b10 5
b10 7
0)
06
1(
19
b0 !
b0 +
b0 8
b0 :
0%
#146
b1 !
b1 +
b1 8
b1 :
0%
#147
b10 !
b10 +
b10 8
b10 :
0(
09
0%
#148
b11 !
b11 +
b11 8
b11 :
0%
#149
b100 !
b100 +
b100 8
b100 :
0%
#150
b101 !
b101 +
b101 8
b101 :
0%
#151
b110 !
b110 +
b110 8
b110 :
0%
#152
b111 !
b111 +
b111 8
b111 :
0%
#153
b1000 !
b1000 +
b1000 8
b1000 :
0%
#154
b1001 !
b1001 +
b1001 8
b1001 :
0%
#155
b11 "
b11 ,
b11 5
b11 7
1(
19
b0 !
b0 +
b0 8
b0 :
0%
#156
b1 !
b1 +
b1 8
b1 :
0%
#157
b10 !
b10 +
b10 8
b10 :
0(
09
0%
#158
b11 !
b11 +
b11 8
b11 :
0%
#159
b100 !
b100 +
b100 8
b100 :
0%
#160
b101 !
b101 +
b101 8
b101 :
0%
#161
b110 !
b110 +
b110 8
b110 :
0%
#162
b111 !
b111 +
b111 8
b111 :
0%
#163
b1000 !
b1000 +
b1000 8
b1000 :
0%
#164
b1001 !
b1001 +
b1001 8
b1001 :
0%
#165
b100 "
b100 ,
b100 5
b100 7
1(
19
b0 !
b0 +
b0 8
b0 :
0%
#166
b1 !
b1 +
b1 8
b1 :
0%
#167
b10 !
b10 +
b10 8
b10 :
0(
09
0%
#168
b11 !
b11 +
b11 8
b11 :
0%
#169
b100 !
b100 +
b100 8
b100 :
0%
#170
b101 !
b101 +
b101 8
b101 :
0%
#171
b110 !
b110 +
b110 8
b110 :
0%
#172
b111 !
b111 +
b111 8
b111 :
0%
#173
b1000 !
b1000 +
b1000 8
b1000 :
0%
#174
b1001 !
b1001 +
b1001 8
b1001 :
0%
#175
b101 "
b101 ,
b101 5
b101 7
1(
19
b0 !
b0 +
b0 8
b0 :
0%
#176
b1 !
b1 +
b1 8
b1 :
0%
#177
b10 !
b10 +
b10 8
b10 :
0(
09
0%
#178
b11 !
b11 +
b11 8
b11 :
0%
#179
b100 !
b100 +
b100 8
b100 :
0%
#180
b101 !
b101 +
b101 8
b101 :
0%
#181
b110 !
b110 +
b110 8
b110 :
0%
#182
b111 !
b111 +
b111 8
b111 :
0%
#183
b1000 !
b1000 +
b1000 8
b1000 :
0%
#184
b1001 !
b1001 +
b1001 8
b1001 :
0%
#185
b11 #
b11 -
b11 2
b11 4
1)
16
b0 "
b0 ,
b0 5
b0 7
1(
19
b0 !
b0 +
b0 8
b0 :
0%
#186
b1 !
b1 +
b1 8
b1 :
0%
#187
b10 !
b10 +
b10 8
b10 :
0(
09
0%
#188
b11 !
b11 +
b11 8
b11 :
0%
#189
b100 !
b100 +
b100 8
b100 :
0%
#190
b101 !
b101 +
b101 8
b101 :
0%
#191
b110 !
b110 +
b110 8
b110 :
0%
#192
b111 !
b111 +
b111 8
b111 :
0%
#193
b1000 !
b1000 +
b1000 8
b1000 :
0%
#194
b1001 !
b1001 +
b1001 8
b1001 :
0%
#195
b1 "
b1 ,
b1 5
b1 7
1(
19
b0 !
b0 +
b0 8
b0 :
0%
#196
b1 !
b1 +
b1 8
b1 :
0%
#197
b10 !
b10 +
b10 8
b10 :
0(
09
0%
#198
b11 !
b11 +
b11 8
b11 :
0%
#199
b100 !
b100 +
b100 8
b100 :
0%
#200
b101 !
b101 +
b101 8
b101 :
0%
#201
b110 !
b110 +
b110 8
b110 :
0%
#202
b111 !
b111 +
b111 8
b111 :
0%
#203
b1000 !
b1000 +
b1000 8
b1000 :
0%
#204
b1001 !
b1001 +
b1001 8
b1001 :
0%
#205
b10 "
b10 ,
b10 5
b10 7
0)
06
1(
19
b0 !
b0 +
b0 8
b0 :
0%
#206
b1 !
b1 +
b1 8
b1 :
0%
#207
b10 !
b10 +
b10 8
b10 :
0(
09
0%
#208
b11 !
b11 +
b11 8
b11 :
0%
#209
b100 !
b100 +
b100 8
b100 :
0%
#210
b101 !
b101 +
b101 8
b101 :
0%
#211
b110 !
b110 +
b110 8
b110 :
0%
#212
b111 !
b111 +
b111 8
b111 :
0%
#213
b1000 !
b1000 +
b1000 8
b1000 :
0%
#214
b1001 !
b1001 +
b1001 8
b1001 :
0%
#215
b11 "
b11 ,
b11 5
b11 7
1(
19
b0 !
b0 +
b0 8
b0 :
0%
#216
b1 !
b1 +
b1 8
b1 :
0%
#217
b10 !
b10 +
b10 8
b10 :
0(
09
0%
#218
b11 !
b11 +
b11 8
b11 :
0%
#219
b100 !
b100 +
b100 8
b100 :
0%
#220
b101 !
b101 +
b101 8
b101 :
0%
#221
b110 !
b110 +
b110 8
b110 :
0%
#222
b111 !
b111 +
b111 8
b111 :
0%
#223
b1000 !
b1000 +
b1000 8
b1000 :
0%
#224
b1001 !
b1001 +
b1001 8
b1001 :
0%
#225
b100 "
b100 ,
b100 5
b100 7
1(
19
b0 !
b0 +
b0 8
b0 :
0%
#226
b1 !
b1 +
b1 8
b1 :
0%
#227
b10 !
b10 +
b10 8
b10 :
0(
09
0%
#228
b11 !
b11 +
b11 8
b11 :
0%
#229
b100 !
b100 +
b100 8
b100 :
0%
#230
b101 !
b101 +
b101 8
b101 :
0%
#231
b110 !
b110 +
b110 8
b110 :
0%
#232
b111 !
b111 +
b111 8
b111 :
0%
#233
b1000 !
b1000 +
b1000 8
b1000 :
0%
#234
b1001 !
b1001 +
b1001 8
b1001 :
0%
#235
b101 "
b101 ,
b101 5
b101 7
1(
19
b0 !
b0 +
b0 8
b0 :
0%
#236
b1 !
b1 +
b1 8
b1 :
0%
#237
b10 !
b10 +
b10 8
b10 :
0(
09
0%
#238
b11 !
b11 +
b11 8
b11 :
0%
#239
b100 !
b100 +
b100 8
b100 :
0%
#240
b101 !
b101 +
b101 8
b101 :
0%
#241
b110 !
b110 +
b110 8
b110 :
0%
#242
b111 !
b111 +
b111 8
b111 :
0%
#243
b1000 !
b1000 +
b1000 8
b1000 :
0%
#244
b1001 !
b1001 +
b1001 8
b1001 :
0%
#245
b100 #
b100 -
b100 2
b100 4
1)
16
b0 "
b0 ,
b0 5
b0 7
1(
19
b0 !
b0 +
b0 8
b0 :
0%
#246
b1 !
b1 +
b1 8
b1 :
0%
#247
b10 !
b10 +
b10 8
b10 :
0(
09
0%
#248
b11 !
b11 +
b11 8
b11 :
0%
#249
b100 !
b100 +
b100 8
b100 :
0%
#250
b101 !
b101 +
b101 8
b101 :
0%
#251
b110 !
b110 +
b110 8
b110 :
0%
#252
b111 !
b111 +
b111 8
b111 :
0%
#253
b1000 !
b1000 +
b1000 8
b1000 :
0%
#254
b1001 !
b1001 +
b1001 8
b1001 :
0%
#255
b1 "
b1 ,
b1 5
b1 7
1(
19
b0 !
b0 +
b0 8
b0 :
0%
#256
b1 !
b1 +
b1 8
b1 :
0%
#257
b10 !
b10 +
b10 8
b10 :
0(
09
0%
#258
b11 !
b11 +
b11 8
b11 :
0%
#259
b100 !
b100 +
b100 8
b100 :
0%
#260
b101 !
b101 +
b101 8
b101 :
0%
#261
b110 !
b110 +
b110 8
b110 :
0%
#262
b111 !
b111 +
b111 8
b111 :
0%
#263
b1000 !
b1000 +
b1000 8
b1000 :
0%
#264
b1001 !
b1001 +
b1001 8
b1001 :
0%
#265
b10 "
b10 ,
b10 5
b10 7
0)
06
1(
19
b0 !
b0 +
b0 8
b0 :
0%
#266
b1 !
b1 +
b1 8
b1 :
0%
#267
b10 !
b10 +
b10 8
b10 :
0(
09
0%
#268
b11 !
b11 +
b11 8
b11 :
0%
#269
b100 !
b100 +
b100 8
b100 :
0%
#270
b101 !
b101 +
b101 8
b101 :
0%
#271
b110 !
b110 +
b110 8
b110 :
0%
#272
b111 !
b111 +
b111 8
b111 :
0%
#273
b1000 !
b1000 +
b1000 8
b1000 :
0%
#274
b1001 !
b1001 +
b1001 8
b1001 :
0%
#275
b11 "
b11 ,
b11 5
b11 7
1(
19
b0 !
b0 +
b0 8
b0 :
0%
#276
b1 !
b1 +
b1 8
b1 :
0%
#277
b10 !
b10 +
b10 8
b10 :
0(
09
0%
#278
b11 !
b11 +
b11 8
b11 :
0%
#279
b100 !
b100 +
b100 8
b100 :
0%
#280
b101 !
b101 +
b101 8
b101 :
0%
#281
b110 !
b110 +
b110 8
b110 :
0%
#282
b111 !
b111 +
b111 8
b111 :
0%
#283
b1000 !
b1000 +
b1000 8
b1000 :
0%
#284
b1001 !
b1001 +
b1001 8
b1001 :
0%
#285
b100 "
b100 ,
b100 5
b100 7
1(
19
b0 !
b0 +
b0 8
b0 :
0%
#286
b1 !
b1 +
b1 8
b1 :
0%
#287
b10 !
b10 +
b10 8
b10 :
0(
09
0%
#288
b11 !
b11 +
b11 8
b11 :
0%
#289
b100 !
b100 +
b100 8
b100 :
0%
#290
b101 !
b101 +
b101 8
b101 :
0%
#291
b110 !
b110 +
b110 8
b110 :
0%
#292
b111 !
b111 +
b111 8
b111 :
0%
#293
b1000 !
b1000 +
b1000 8
b1000 :
0%
#294
b1001 !
b1001 +
b1001 8
b1001 :
0%
#295
b101 "
b101 ,
b101 5
b101 7
1(
19
b0 !
b0 +
b0 8
b0 :
0%
#296
b1 !
b1 +
b1 8
b1 :
0%
#297
b10 !
b10 +
b10 8
b10 :
0(
09
0%
#298
b11 !
b11 +
b11 8
b11 :
0%
#299
b100 !
b100 +
b100 8
b100 :
0%
#300
b101 !
b101 +
b101 8
b101 :
0%
#301
b110 !
b110 +
b110 8
b110 :
0%
#302
b111 !
b111 +
b111 8
b111 :
0%
#303
b1000 !
b1000 +
b1000 8
b1000 :
0%
#304
b1001 !
b1001 +
b1001 8
b1001 :
0%
#305
b101 #
b101 -
b101 2
b101 4
1)
16
b0 "
b0 ,
b0 5
b0 7
1(
19
b0 !
b0 +
b0 8
b0 :
0%
#306
b1 !
b1 +
b1 8
b1 :
0%
#307
b10 !
b10 +
b10 8
b10 :
0(
09
0%
#308
b11 !
b11 +
b11 8
b11 :
0%
#309
b100 !
b100 +
b100 8
b100 :
0%
#310
b101 !
b101 +
b101 8
b101 :
0%
#311
b110 !
b110 +
b110 8
b110 :
0%
#312
b111 !
b111 +
b111 8
b111 :
0%
#313
b1000 !
b1000 +
b1000 8
b1000 :
0%
#314
b1001 !
b1001 +
b1001 8
b1001 :
0%
#315
b1 "
b1 ,
b1 5
b1 7
1(
19
b0 !
b0 +
b0 8
b0 :
0%
#316
b1 !
b1 +
b1 8
b1 :
0%
#317
b10 !
b10 +
b10 8
b10 :
0(
09
0%
#318
b11 !
b11 +
b11 8
b11 :
0%
#319
b100 !
b100 +
b100 8
b100 :
0%
#320
b101 !
b101 +
b101 8
b101 :
0%
#321
b110 !
b110 +
b110 8
b110 :
0%
#322
b111 !
b111 +
b111 8
b111 :
0%
#323
b1000 !
b1000 +
b1000 8
b1000 :
0%
#324
b1001 !
b1001 +
b1001 8
b1001 :
0%
#325
b10 "
b10 ,
b10 5
b10 7
0)
06
1(
19
b0 !
b0 +
b0 8
b0 :
0%
#326
b1 !
b1 +
b1 8
b1 :
0%
#327
b10 !
b10 +
b10 8
b10 :
0(
09
0%
#328
b11 !
b11 +
b11 8
b11 :
0%
#329
b100 !
b100 +
b100 8
b100 :
0%
#330
b101 !
b101 +
b101 8
b101 :
0%
#331
b110 !
b110 +
b110 8
b110 :
0%
#332
b111 !
b111 +
b111 8
b111 :
0%
#333
b1000 !
b1000 +
b1000 8
b1000 :
0%
#334
b1001 !
b1001 +
b1001 8
b1001 :
0%
#335
b11 "
b11 ,
b11 5
b11 7
1(
19
b0 !
b0 +
b0 8
b0 :
0%
#336
b1 !
b1 +
b1 8
b1 :
0%
#337
b10 !
b10 +
b10 8
b10 :
0(
09
0%
#338
b11 !
b11 +
b11 8
b11 :
0%
#339
b100 !
b100 +
b100 8
b100 :
0%
#340
b101 !
b101 +
b101 8
b101 :
0%
#341
b110 !
b110 +
b110 8
b110 :
0%
#342
b111 !
b111 +
b111 8
b111 :
0%
#343
b1000 !
b1000 +
b1000 8
b1000 :
0%
#344
b1001 !
b1001 +
b1001 8
b1001 :
0%
#345
b100 "
b100 ,
b100 5
b100 7
1(
19
b0 !
b0 +
b0 8
b0 :
0%
#346
b1 !
b1 +
b1 8
b1 :
0%
#347
b10 !
b10 +
b10 8
b10 :
0(
09
0%
#348
b11 !
b11 +
b11 8
b11 :
0%
#349
b100 !
b100 +
b100 8
b100 :
0%
#350
b101 !
b101 +
b101 8
b101 :
0%
#351
b110 !
b110 +
b110 8
b110 :
0%
#352
b111 !
b111 +
b111 8
b111 :
0%
#353
b1000 !
b1000 +
b1000 8
b1000 :
0%
#354
b1001 !
b1001 +
b1001 8
b1001 :
0%
#355
b101 "
b101 ,
b101 5
b101 7
1(
19
b0 !
b0 +
b0 8
b0 :
0%
#356
b1 !
b1 +
b1 8
b1 :
0%
#357
b10 !
b10 +
b10 8
b10 :
0(
09
0%
#358
b11 !
b11 +
b11 8
b11 :
0%
#359
b100 !
b100 +
b100 8
b100 :
0%
#360
b101 !
b101 +
b101 8
b101 :
0%
#361
b110 !
b110 +
b110 8
b110 :
0%
#362
b111 !
b111 +
b111 8
b111 :
0%
#363
b1000 !
b1000 +
b1000 8
b1000 :
0%
#364
b1001 !
b1001 +
b1001 8
b1001 :
0%
#365
b110 #
b110 -
b110 2
b110 4
1)
16
b0 "
b0 ,
b0 5
b0 7
1(
19
b0 !
b0 +
b0 8
b0 :
0%
#366
b1 !
b1 +
b1 8
b1 :
0%
#367
b10 !
b10 +
b10 8
b10 :
0(
09
0%
#368
b11 !
b11 +
b11 8
b11 :
0%
#369
b100 !
b100 +
b100 8
b100 :
0%
#370
b101 !
b101 +
b101 8
b101 :
0%
#371
b110 !
b110 +
b110 8
b110 :
0%
#372
b111 !
b111 +
b111 8
b111 :
0%
#373
b1000 !
b1000 +
b1000 8
b1000 :
0%
#374
b1001 !
b1001 +
b1001 8
b1001 :
0%
#375
b1 "
b1 ,
b1 5
b1 7
1(
19
b0 !
b0 +
b0 8
b0 :
0%
#376
b1 !
b1 +
b1 8
b1 :
0%
#377
b10 !
b10 +
b10 8
b10 :
0(
09
0%
#378
b11 !
b11 +
b11 8
b11 :
0%
#379
b100 !
b100 +
b100 8
b100 :
0%
#380
b101 !
b101 +
b101 8
b101 :
0%
#381
b110 !
b110 +
b110 8
b110 :
0%
#382
b111 !
b111 +
b111 8
b111 :
0%
#383
b1000 !
b1000 +
b1000 8
b1000 :
0%
#384
b1001 !
b1001 +
b1001 8
b1001 :
0%
#385
b10 "
b10 ,
b10 5
b10 7
0)
06
1(
19
b0 !
b0 +
b0 8
b0 :
0%
#386
b1 !
b1 +
b1 8
b1 :
0%
#387
b10 !
b10 +
b10 8
b10 :
0(
09
0%
#388
b11 !
b11 +
b11 8
b11 :
0%
#389
b100 !
b100 +
b100 8
b100 :
0%
#390
b101 !
b101 +
b101 8
b101 :
0%
#391
b110 !
b110 +
b110 8
b110 :
0%
#392
b111 !
b111 +
b111 8
b111 :
0%
#393
b1000 !
b1000 +
b1000 8
b1000 :
0%
#394
b1001 !
b1001 +
b1001 8
b1001 :
0%
#395
b11 "
b11 ,
b11 5
b11 7
1(
19
b0 !
b0 +
b0 8
b0 :
0%
#396
b1 !
b1 +
b1 8
b1 :
0%
#397
b10 !
b10 +
b10 8
b10 :
0(
09
0%
#398
b11 !
b11 +
b11 8
b11 :
0%
#399
b100 !
b100 +
b100 8
b100 :
0%
#400
b101 !
b101 +
b101 8
b101 :
0%
#401
b110 !
b110 +
b110 8
b110 :
0%
#402
b111 !
b111 +
b111 8
b111 :
0%
#403
b1000 !
b1000 +
b1000 8
b1000 :
0%
#404
b1001 !
b1001 +
b1001 8
b1001 :
0%
#405
b100 "
b100 ,
b100 5
b100 7
1(
19
b0 !
b0 +
b0 8
b0 :
0%
#406
b1 !
b1 +
b1 8
b1 :
0%
#407
b10 !
b10 +
b10 8
b10 :
0(
09
0%
#408
b11 !
b11 +
b11 8
b11 :
0%
#409
b100 !
b100 +
b100 8
b100 :
0%
#410
b101 !
b101 +
b101 8
b101 :
0%
#411
b110 !
b110 +
b110 8
b110 :
0%
#412
b111 !
b111 +
b111 8
b111 :
0%
#413
b1000 !
b1000 +
b1000 8
b1000 :
0%
#414
b1001 !
b1001 +
b1001 8
b1001 :
0%
#415
b101 "
b101 ,
b101 5
b101 7
1(
19
b0 !
b0 +
b0 8
b0 :
0%
#416
b1 !
b1 +
b1 8
b1 :
0%
#417
b10 !
b10 +
b10 8
b10 :
0(
09
0%
#418
b11 !
b11 +
b11 8
b11 :
0%
#419
b100 !
b100 +
b100 8
b100 :
0%
